nonebot_plugin_eventmonitor/__init__.py
nonebot_plugin_eventmonitor/chuo_message.py
nonebot_plugin_eventmonitor/config.py
nonebot_plugin_eventmonitor/fonts/SIMYOU.TTF
nonebot_plugin_eventmonitor/handle.py
nonebot_plugin_eventmonitor/matcher.py
nonebot_plugin_eventmonitor/txt2img.py
nonebot_plugin_eventmonitor-0.4.9.dist-info/LICENSE
nonebot_plugin_eventmonitor-0.4.9.dist-info/METADATA
nonebot_plugin_eventmonitor-0.4.9.dist-info/WHEEL
nonebot_plugin_eventmonitor-0.4.9.dist-info/RECORD
