Metadata-Version: 2.3
Name: nonebot-plugin-eventmonitor
Version: 0.4.9
Summary: 监控群事件的插件 For Nonebot2
License: MIT License
Author: Reversedeer
Author-email: ysjvillmark@gmail.com
Requires-Python: >=3.9,<4.0
Classifier: License :: Other/Proprietary License
Classifier: Programming Language :: Python :: 3
Classifier: Programming Language :: Python :: 3.9
Classifier: Programming Language :: Python :: 3.10
Classifier: Programming Language :: Python :: 3.11
Classifier: Programming Language :: Python :: 3.12
Classifier: Programming Language :: Python :: 3.13
Requires-Dist: httpx[http2] (>=0.27.2,<1.0.0)
Requires-Dist: nonebot-adapter-onebot (>=2.2.0)
Requires-Dist: nonebot-plugin-apscheduler (>=0.1.3)
Requires-Dist: nonebot-plugin-localstore (>=0.6.0)
Requires-Dist: nonebot2[fastapi] (>=2.2.0)
Requires-Dist: packaging (>=24.2)
Requires-Dist: pillow (>=9.4.0)
Requires-Dist: pydantic (>=1.10.0,!=2.5.0,!=2.5.1,!=2.10.0,<3.0.0)
Project-URL: Homepage, https://github.com/Reversedeer/nonebot_plugin_eventmonitor
Project-URL: Issues, https://github.com/Reversedeer/nonebot_plugin_eventmonitor/issues
Project-URL: Repository, https://github.com/Reversedeer/nonebot_plugin_eventmonitor.git
